facebook_plugin_banyan/__init__.py
facebook_plugin_banyan/facebook_plugin.py
fb_account_promote_plugin_banyan-0.0.9.dist-info/entry_points.txt
fb_account_promote_plugin_banyan-0.0.9.dist-info/METADATA
fb_account_promote_plugin_banyan-0.0.9.dist-info/WHEEL
fb_account_promote_plugin_banyan-0.0.9.dist-info/RECORD
